IOCFramework/__init__.py
IOCFramework/exceptions/BindingResolutionException.py
IOCFramework/exceptions/NameResolutionException.py
IOCFramework/exceptions/__init__.py
IOCFramework/src/__init__.py
IOCFramework/src/app.py
IOCFramework/src/resolve.py
tests/feature/__init__.py
tests/feature/test_resolution.py
tests/unit/__init__.py
tests/unit/test_app.py
tests/unit/test_resolve.py
iocframework-1.0.0.dist-info/LICENSE
iocframework-1.0.0.dist-info/METADATA
iocframework-1.0.0.dist-info/WHEEL
iocframework-1.0.0.dist-info/top_level.txt
iocframework-1.0.0.dist-info/RECORD
