Metadata-Version: 2.1
Name: iocframework
Version: 1.0.0
Summary: Read the latest Real Python tutorials
Home-page: https://github.com/dino16m/iocframework
Author: Dino16m
Author-email: anselem16m@gmail.com
License: MIT
Platform: UNKNOWN
Classifier: License :: OSI Approved :: MIT License
Classifier: Programming Language :: Python :: 3
Classifier: Programming Language :: Python :: 3.7
